misterio/__init__.py
misterio/misterio.py
misterio/misterio_util.py
misterio-0.1.3.dist-info/entry_points.txt
misterio-0.1.3.dist-info/licenses/LICENSE
misterio-0.1.3.dist-info/WHEEL
misterio-0.1.3.dist-info/METADATA
misterio-0.1.3.dist-info/RECORD
