Metadata-Version: 2.4
Name: misterio
Version: 0.1.3
Summary: misterio CLI
Author-email: Giovanni Giorgi <jj@gioorgi.com>
Requires-Python: >=3.10
License-Expression: MIT
Classifier: Programming Language :: Python :: 3
Classifier: Operating System :: OS Independent
License-File: LICENSE
Requires-Dist: click>=8.2.1
